ovos_audio/__init__.py
ovos_audio/__main__.py
ovos_audio/audio.py
ovos_audio/playback.py
ovos_audio/service.py
ovos_audio/transformers.py
ovos_audio/tts.py
ovos_audio/utils.py
ovos_audio/version.py
ovos_audio/res/snd/acknowledge.mp3
ovos_audio/res/snd/blop-mark-diangelo.wav
ovos_audio/res/snd/error.mp3
ovos_audio/res/snd/start_listening.wav
ovos_audio-1.1.1.dist-info/licenses/LICENSE.md
ovos_audio-1.1.1.dist-info/METADATA
ovos_audio-1.1.1.dist-info/WHEEL
ovos_audio-1.1.1.dist-info/entry_points.txt
ovos_audio-1.1.1.dist-info/top_level.txt
ovos_audio-1.1.1.dist-info/RECORD
