Metadata-Version: 2.4
Name: ovos_audio
Version: 1.1.1
Summary: ovos-core audio daemon client
Home-page: https://github.com/OpenVoiceOS/ovos-audio
License: Apache-2.0
Classifier: Development Status :: 4 - Beta
Classifier: Programming Language :: Python :: 3
Classifier: License :: OSI Approved :: Apache Software License
License-File: LICENSE.md
Requires-Dist: ovos-utils<1.0.0,>=0.0.38
Requires-Dist: ovos_bus_client<2.0.0,>=0.0.8
Requires-Dist: ovos-config<3.0.0,>=0.0.12
Requires-Dist: ovos-plugin-manager<3.0.0,>=0.0.26
Provides-Extra: extras
Requires-Dist: ovos-dialog-normalizer-plugin<1.0.0,>=0.0.1; extra == "extras"
Requires-Dist: ovos-tts-plugin-server<1.0.0,>=0.0.2; extra == "extras"
Requires-Dist: ovos-tts-plugin-piper<1.0.0,>=0.2.4; extra == "extras"
Requires-Dist: ovos_audio_plugin_simple<1.0.0,>=0.1.0; extra == "extras"
Requires-Dist: ovos-audio-plugin-mpv<1.0.0,>=0.2.0; extra == "extras"
Requires-Dist: ovos-media-plugin-spotify<1.0.0,>=0.2.3; extra == "extras"
Requires-Dist: ovos-media-plugin-chromecast<1.0.0,>=0.1.0; extra == "extras"
Requires-Dist: ovos_plugin_common_play[extractors]<2.0.0,>=1.1.4; extra == "extras"
Dynamic: classifier
Dynamic: description
Dynamic: description-content-type
Dynamic: home-page
Dynamic: license
Dynamic: license-file
Dynamic: provides-extra
Dynamic: requires-dist
Dynamic: summary
